reqsnap/__init__.py
reqsnap/cli.py
reqsnap/core.py
reqsnap/exception/__init__.py
reqsnap/logger/__init__.py
reqsnap/utils/__init__.py
tests/__init__.py
tests/test_basic.py
tests/test_cli.py
tests/test_formats.py
tests/test_integration.py
reqsnap-1.0.0.dist-info/LICENSE
reqsnap-1.0.0.dist-info/METADATA
reqsnap-1.0.0.dist-info/WHEEL
reqsnap-1.0.0.dist-info/entry_points.txt
reqsnap-1.0.0.dist-info/top_level.txt
reqsnap-1.0.0.dist-info/RECORD
