Metadata-Version: 2.1
Name: reqsnap
Version: 1.0.0
Summary: Python Requirements Snapshot Tool - Lock exact versions of main libraries
Home-page: https://github.com/Ahmed2797/PyPI-Package---Requirements-snapshot-
Author: Ahmed2797
Author-email: Ahmed2797 <tanvirahmed754575@gmail.com>
License: MIT
Classifier: Development Status :: 5 - Production/Stable
Classifier: Intended Audience :: Developers
Classifier: License :: OSI Approved :: MIT License
Classifier: Programming Language :: Python :: 3
Classifier: Operating System :: OS Independent
Requires-Python: >=3.7
License-File: LICENSE
Requires-Dist: importlib-metadata >=4.0.0
Requires-Dist: pyyaml >=6.0
Requires-Dist: toml >=0.10.0
Requires-Dist: packaging >=21.0
Provides-Extra: dev
Requires-Dist: pytest >=7.0.0 ; extra == 'dev'
Requires-Dist: black >=23.0.0 ; extra == 'dev'
Requires-Dist: flake8 >=6.0.0 ; extra == 'dev'
Requires-Dist: mypy >=1.0.0 ; extra == 'dev'
